setup.py
zyytif/__init__.py
zyytif/zyytif.py
zyytif.egg-info/PKG-INFO
zyytif.egg-info/SOURCES.txt
zyytif.egg-info/dependency_links.txt
zyytif.egg-info/requires.txt
zyytif.egg-info/top_level.txt
zyytif.egg-info/zip-safe