Metadata-Version: 1.2
Name: zyytif
Version: 0.1.2
Summary: Scientific computing for TIF
Home-page: UNKNOWN
Author: Franklin
Author-email: franklinzhang@foxmail.com
Maintainer: Franklin
Maintainer-email: franklinzhang@foxmail.com
License: MIT License
Platform: all
Classifier: Operating System :: OS Independent
Classifier: Intended Audience :: Developers
Classifier: License :: OSI Approved :: MIT License
Classifier: Programming Language :: Python :: 3
Classifier: Programming Language :: Python :: 3.4
Classifier: Programming Language :: Python :: 3.5
Classifier: Programming Language :: Python :: 3.6
Classifier: Programming Language :: Python :: 3.7
Classifier: Topic :: Software Development :: Libraries
